{
	"class" : {
		"extension" : "dkh 4/4/2012 14:19",
		"monticelloMetaDirName" : "dkh 4/4/2012 17:44" },
	"instance" : {
		"addClassAndMethodDefinitionsFromDirectory:" : "dkh 4/4/2012 10:27",
		"addClassAndMethodDefinitionsFromEntry:" : "dkh 6/27/2012 14:30",
		"addClassDefinitionFrom:comment:" : "dkh 6/27/2012 14:18",
		"addExtensionClassAndMethodDefinitionsFromEntry:" : "dkh 6/12/2012 17:33:23",
		"addMethodDefinitionsForClass:methodProperties:in:" : "dkh 6/12/2012 17:33:23",
		"basicVersion" : "dkh 6/27/2012 13:59",
		"loadDefinitions" : "dkh 6/27/2012 14:59",
		"loadPackage" : "dkh 6/27/2012 13:57",
		"loadVersionInfo" : "dkh 6/27/2012 14:48",
		"methodSelectorFor:" : "dkh 4/4/2012 11:29",
		"packageNameFromPackageDirectory" : "dkh 6/27/2012 13:49" } }
