{
	"class" : {
		 },
	"instance" : {
		"baseDefinitions" : "ThierryGoubier 1/6/2016 18:39:16",
		"baseDefinitionsWithClassDefinition:" : "ThierryGoubier 1/6/2016 18:39:16",
		"targetDefinitions" : "ThierryGoubier 1/6/2016 18:39:16",
		"targetDefinitionsWithClassDefinition:" : "ThierryGoubier 1/6/2016 18:39:16",
		"tearDownPackagesList" : "ThierryGoubier 1/6/2016 18:39:16",
		"testBaseLoad" : "ThierryGoubier 1/6/2016 18:39:16",
		"testBaseLoadRepository" : "ThierryGoubier 1/6/2016 18:39:16",
		"testCypress2CuisLoad" : "ThierryGoubier 1/6/2016 18:39:16",
		"testIssue74" : "ThierryGoubier 1/6/2016 18:39:16",
		"testTargetLoad" : "ThierryGoubier 1/6/2016 18:39:16",
		"testTargetLoadRepository" : "ThierryGoubier 1/6/2016 18:39:16",
		"validateAgainst:for:" : "ThierryGoubier 1/6/2016 18:39:16" } }
